simpyx/__init__.py
simpyx/__version__.py
simpyx/pixels.py
simpyx/screen.py
simpyx/shows.py
simpyx-1.1.0.dist-info/METADATA
simpyx-1.1.0.dist-info/WHEEL
simpyx-1.1.0.dist-info/licenses/LICENSE
simpyx-1.1.0.dist-info/RECORD
