Metadata-Version: 2.3
Name: simpyx
Version: 1.1.0
Summary: Simulate neopixels in the terminal.
Project-URL: Homepage, https://github.com/jtompkin/simpyx
Author-email: Josh Tompkin <jtompkin-dev@pm.me>
License: MIT License
License-File: LICENSE
Keywords: led,neopixel,simulate,terminal
Classifier: Environment :: Console
Classifier: License :: OSI Approved :: MIT License
Classifier: Programming Language :: Python :: 3
Classifier: Programming Language :: Python :: 3.10
Classifier: Programming Language :: Python :: 3.11
Classifier: Programming Language :: Python :: 3.12
Classifier: Programming Language :: Python :: 3.13
Classifier: Typing :: Typed
Requires-Python: >=3.10
